Lab-3/mux_4_1_logic.v
module mux_4_1_logic (

	// Inputs
	input [3:0] IN,
	input [1:0] S,
	input EN,
	
	// Outputs
	output Y
);
	wire x0, x1, x2, x3;

	assign x3 = (EN)&(S[0])&(S[1])&(IN[3]);
	assign x2 = (EN)&(~S[0])&(S[1])&(IN[2]);
	assign x1 = (EN)&(S[0])&(~S[1])&(IN[1]);
	assign x0 = (EN)&(~S[0])&(~S[1])&(IN[0]);

	assign Y = x3 | x2 | x1 | x0;

endmodule

Lab-3/mux_4_1_logic_tb.v
`include "mux_4_1_logic.v"
`timescale 1ns/1ps // time unit / simulation precision

module mux_4_1_logic_tb;

	reg [3:0] IN;
	reg [1:0] S;
	reg EN;
	wire Y;

	mux_4_1_logic uut (IN, S, EN, Y);

	initial begin
		$dumpfile("mux_4_1_logic_tb.vcd");
		$dumpvars(0, mux_4_1_logic_tb);
	end

	initial begin
		EN = 1; IN = 3; S = 0; #1
		EN = 1; IN = 3; S = 1; #1
		EN = 1; IN = 3; S = 2; #1
		EN = 1; IN = 3; S = 3; #1
		EN = 1; IN = 4; S = 0; #1
		EN = 1; IN = 7; S = 1; #1
		EN = 1; IN = 2; S = 2; #1
		EN = 1; IN = 8; S = 3; #1
		
		$finish;
	end

endmodule

Lab-3/mux_4_1_logic_tb.vcd
$date
	Thu Sep  1 14:07:53 2022
$end
$version
	Icarus Verilog
$end
$timescale
	1ps
$end
$scope module mux_4_1_logic_tb $end
$var wire 1 ! Y $end
$var reg 1 " EN $end
$var reg 4 # IN [3:0] $end
$var reg 2 $ S [1:0] $end
$scope module uut $end
$var wire 1 " EN $end
$var wire 4 % IN [3:0] $end
$var wire 2 & S [1:0] $end
$var wire 1 ! Y $end
$var wire 1 ' x0 $end
$var wire 1 ( x1 $end
$var wire 1 ) x2 $end
$var wire 1 * x3 $end
$upscope $end
$upscope $end
$enddefinitions $end
#0
$dumpvars
0*
0)
0(
1'
b0 &
b11 %
b0 $
b11 #
1"
1!
$end
#1000
0'
1(
b1 $
b1 &
#2000
0!
0(
b10 $
b10 &
#3000
b11 $
b11 &
#4000
b0 $
b0 &
b100 #
b100 %
#5000
1(
1!
0'
b1 $
b1 &
b111 #
b111 %
#6000
0!
0(
b10 $
b10 &
b10 #
b10 %
#7000
1!
1*
b11 $
b11 &
b1000 #
b1000 %
